{
  "type": "forge:conditional",
  "recipes": [
    {
      "conditions": [
        {
          "type": "forge:mod_loaded",
          "modid": "advanced_ae"
        }
      ],
      "recipe": {
        "type": "minecraft:crafting_shaped",
        "pattern": [
          "ABA",
          "BCB",
          "ABA"
        ],
        "key": {
          "A": {
            "item": "advanced_ae:quantum_alloy_plate"
          },
          "B": {
            "item": "minecraft:dragon_breath"
          },
          "C": {
            "item": "ae2:speed_card"
          }
        },
        "result": {
          "item": "ae2_overclocked:overclock_card"
        }
      }
    },
    {
      "conditions": [
        {
          "type": "forge:true"
        }
      ],
      "recipe": {
        "type": "minecraft:crafting_shaped",
        "pattern": [
          "ABA",
          "BCB",
          "ABA"
        ],
        "key": {
          "A": {
            "item": "ae2:singularity"
          },
          "B": {
            "item": "minecraft:dragon_breath"
          },
          "C": {
            "item": "ae2:speed_card"
          }
        },
        "result": {
          "item": "ae2_overclocked:overclock_card"
        }
      }
    }
  ]
}
